postProcessingGEP/__init__.py
postProcessingGEP/postprocess.py
postProcessingGEP-1.0.0.dist-info/LICENSE
postProcessingGEP-1.0.0.dist-info/METADATA
postProcessingGEP-1.0.0.dist-info/WHEEL
postProcessingGEP-1.0.0.dist-info/top_level.txt
postProcessingGEP-1.0.0.dist-info/RECORD
