Metadata-Version: 2.1
Name: postProcessingGEP
Version: 1.0.0
Summary: A package for postprocessing text
Home-page: https://github.com/vanshajsingla03/postProcessingGEP
Author: Vanshaj Singla
Author-email: vanshaj.singla@gep.com
Classifier: Programming Language :: Python :: 3
Classifier: License :: OSI Approved :: MIT License
Classifier: Operating System :: OS Independent
Requires-Python: >=3.6
License-File: LICENSE
